README.md
setup.py
./logserver.py
logserver.egg-info/PKG-INFO
logserver.egg-info/SOURCES.txt
logserver.egg-info/dependency_links.txt
logserver.egg-info/top_level.txt