Metadata-Version: 1.1
Name: logserver
Version: 0.1.0
Summary: A simple socket-based log server based on the Python logging cookbook.
Home-page: https://github.com/luismsgomes/logserver
Author: Luís Gomes
Author-email: luismsgomes@gmail.com
License: GPLv3
Keywords: logging util
Platform: UNKNOWN
Classifier: Development Status :: 4 - Beta
Classifier: License :: OSI Approved :: GNU General Public License v3 (GPLv3)
Classifier: Programming Language :: Python :: 3.8
